{
   "apiVersion": "route.openshift.io/v1",
   "kind": "Route",
   "metadata": {
      "annotations": {
         "haproxy.router.openshift.io/timeout": "60s"
      },
      "labels": {
         "org.eclipse.cbi.jiro/project.fullName": "modeling.acceleo",
         "org.eclipse.cbi.jiro/project.shortname": "acceleo"
      },
      "name": "acceleo",
      "namespace": "acceleo"
   },
   "spec": {
      "host": "ci-staging.eclipse.org",
      "path": "/acceleo",
      "port": {
         "targetPort": "http"
      },
      "tls": {
         "insecureEdgeTerminationPolicy": "Redirect",
         "termination": "edge"
      },
      "to": {
         "kind": "Service",
         "name": "jenkins-ui",
         "weight": 100
      }
   }
}
