{
   "apiVersion": "v1",
   "kind": "ResourceQuota",
   "metadata": {
      "labels": {
         "org.eclipse.cbi.jiro/project.fullName": "adoptium.temurin-compliance",
         "org.eclipse.cbi.jiro/project.shortname": "temurin-compliance"
      },
      "name": "jenkins-instance-quota",
      "namespace": "temurin-compliance"
   },
   "spec": {
      "hard": {
         "limits.cpu": "8100m",
         "limits.memory": "13312Mi",
         "pods": 3,
         "requests.cpu": "4150m",
         "requests.memory": "13312Mi"
      }
   }
}
