{
   "apiVersion": "v1",
   "kind": "Service",
   "metadata": {
      "labels": {
         "org.eclipse.cbi.jiro/project.fullName": "modeling.mdt.etrice",
         "org.eclipse.cbi.jiro/project.shortname": "etrice"
      },
      "name": "jenkins-ui",
      "namespace": "etrice"
   },
   "spec": {
      "ports": [
         {
            "name": "http",
            "port": 80,
            "protocol": "TCP",
            "targetPort": 8080
         }
      ],
      "selector": {
         "org.eclipse.cbi.jiro/project.fullName": "modeling.mdt.etrice"
      }
   }
}
