{
   "apiVersion": "v1",
   "kind": "Role",
   "metadata": {
      "labels": {
         "org.eclipse.cbi.jiro/project.fullName": "technology.package-drone",
         "org.eclipse.cbi.jiro/project.shortname": "package-drone"
      },
      "name": "jenkins-master-owner",
      "namespace": "package-drone"
   },
   "rules": [
      {
         "apiGroups": [
            ""
         ],
         "resources": [
            "pods",
            "pods/exec"
         ],
         "verbs": [
            "create",
            "delete",
            "get",
            "list",
            "patch",
            "update",
            "watch"
         ]
      },
      {
         "apiGroups": [
            ""
         ],
         "resources": [
            "pods/log",
            "events"
         ],
         "verbs": [
            "get",
            "list",
            "watch"
         ]
      }
   ]
}
